_black_version.py
black.py
blackd.py
blib2to3/Grammar.txt
blib2to3/PatternGrammar.txt
blib2to3/__init__.py
blib2to3/pygram.py
blib2to3/pytree.py
blib2to3/pgen2/__init__.py
blib2to3/pgen2/conv.py
blib2to3/pgen2/driver.py
blib2to3/pgen2/grammar.py
blib2to3/pgen2/literals.py
blib2to3/pgen2/parse.py
blib2to3/pgen2/pgen.py
blib2to3/pgen2/token.py
blib2to3/pgen2/tokenize.py
axblack-20220330.dist-info/LICENSE
axblack-20220330.dist-info/METADATA
axblack-20220330.dist-info/WHEEL
axblack-20220330.dist-info/entry_points.txt
axblack-20220330.dist-info/top_level.txt
axblack-20220330.dist-info/RECORD
